migrations/0001_initial.py
migrations/__init__.py
django_aligo-0.1.2.dist-info/LICENSE
django_aligo-0.1.2.dist-info/METADATA
django_aligo-0.1.2.dist-info/WHEEL
django_aligo-0.1.2.dist-info/top_level.txt
django_aligo-0.1.2.dist-info/RECORD
